proofofthought-1.0.1.dist-info/licenses/LICENSE
z3adapter/__init__.py
z3adapter/_version.py
z3adapter/cli.py
z3adapter/interpreter.py
z3adapter/backends/__init__.py
z3adapter/backends/abstract.py
z3adapter/backends/json_backend.py
z3adapter/backends/smt2_backend.py
z3adapter/dsl/__init__.py
z3adapter/dsl/expressions.py
z3adapter/dsl/sorts.py
z3adapter/optimization/__init__.py
z3adapter/optimization/optimizer.py
z3adapter/postprocessors/__init__.py
z3adapter/postprocessors/abstract.py
z3adapter/postprocessors/decomposed.py
z3adapter/postprocessors/least_to_most.py
z3adapter/postprocessors/registry.py
z3adapter/postprocessors/self_consistency.py
z3adapter/postprocessors/self_refine.py
z3adapter/reasoning/__init__.py
z3adapter/reasoning/evaluation.py
z3adapter/reasoning/program_generator.py
z3adapter/reasoning/prompt_template.py
z3adapter/reasoning/proof_of_thought.py
z3adapter/reasoning/smt2_prompt_template.py
z3adapter/reasoning/verifier.py
z3adapter/security/__init__.py
z3adapter/security/validator.py
z3adapter/solvers/__init__.py
z3adapter/solvers/abstract.py
z3adapter/solvers/z3_solver.py
z3adapter/verification/__init__.py
z3adapter/verification/verifier.py
proofofthought-1.0.1.dist-info/METADATA
proofofthought-1.0.1.dist-info/WHEEL
proofofthought-1.0.1.dist-info/top_level.txt
proofofthought-1.0.1.dist-info/RECORD
