Metadata-Version: 2.4
Name: proofofthought
Version: 1.0.1
Summary: LLM-based reasoning using Z3 theorem proving
Author-email: Debargha Ganguly <debargha@case.edu>
License: MIT
Project-URL: Homepage, https://github.com/debarghaG/proofofthought
Project-URL: Documentation, https://github.com/debarghaG/proofofthought#readme
Project-URL: Repository, https://github.com/debarghaG/proofofthought
Project-URL: Bug Tracker, https://github.com/debarghaG/proofofthought/issues
Keywords: llm,reasoning,z3,theorem-proving,smt,ai
Classifier: Development Status :: 4 - Beta
Classifier: Intended Audience :: Developers
Classifier: Intended Audience :: Science/Research
Classifier: License :: OSI Approved :: MIT License
Classifier: Programming Language :: Python :: 3
Classifier: Programming Language :: Python :: 3.12
Classifier: Topic :: Scientific/Engineering :: Artificial Intelligence
Classifier: Topic :: Software Development :: Libraries :: Python Modules
Requires-Python: >=3.12
License-File: LICENSE
Requires-Dist: z3-solver>=4.15.0
Requires-Dist: openai>=2.0.0
Requires-Dist: scikit-learn>=1.7.0
Requires-Dist: numpy>=2.3.0
Requires-Dist: python-dotenv>=1.0.0
Provides-Extra: dev
Requires-Dist: black>=25.9.0; extra == "dev"
Requires-Dist: ruff>=0.13.0; extra == "dev"
Requires-Dist: mypy>=1.18.0; extra == "dev"
Requires-Dist: pre-commit>=4.3.0; extra == "dev"
Requires-Dist: pytest>=8.0.0; extra == "dev"
Dynamic: license-file
